lazynwb/__init__.py
lazynwb/attrs.py
lazynwb/base.py
lazynwb/conversion.py
lazynwb/dandi.py
lazynwb/exceptions.py
lazynwb/file_io.py
lazynwb/lazyframe.py
lazynwb/py.typed
lazynwb/tables.py
lazynwb/timeseries.py
lazynwb/types_.py
lazynwb/utils.py
lazynwb-0.2.77.dist-info/licenses/LICENSE
lazynwb-0.2.77.dist-info/METADATA
lazynwb-0.2.77.dist-info/WHEEL
lazynwb-0.2.77.dist-info/entry_points.txt
lazynwb-0.2.77.dist-info/top_level.txt
lazynwb-0.2.77.dist-info/RECORD
