Metadata-Version: 2.4
Name: lazynwb
Version: 0.2.77
Summary: An attempt to speed-up access to large NWB (Neurodata Without Borders) files stored in the cloud.
Author-email: Ben Hardcastle <ben.hardcastle@alleninstitue.org>
License: MIT
Project-URL: Repository, https://github.com/bjhardcastle/lazynwb
Project-URL: Issues, https://github.com/bjhardcastle/lazynwb/issues
Classifier: Development Status :: 3 - Alpha
Classifier: Programming Language :: Python :: 3
Classifier: Programming Language :: Python :: 3.9
Classifier: Programming Language :: Python :: 3.10
Classifier: Programming Language :: Python :: 3.11
Classifier: License :: OSI Approved :: MIT License
Classifier: Operating System :: Microsoft :: Windows
Classifier: Operating System :: POSIX :: Linux
Requires-Python: >=3.9
License-File: LICENSE
Requires-Dist: h5py>=3.10.0
Requires-Dist: zarr<3.0,>=2.17.0
Requires-Dist: numcodecs<0.16
Requires-Dist: remfile>=0.1.10
Requires-Dist: tqdm>=4.66.2
Requires-Dist: pandas>=2.0.0
Requires-Dist: polars[pandas]>1.32.0
Requires-Dist: pydantic>=2.11.6
Requires-Dist: universal-pathlib>=0.1.4
Requires-Dist: dotenv>=0.9.9
Requires-Dist: s3fs>=2025.7.0
Requires-Dist: requests>=2.32.4
Dynamic: license-file
